terrastack/__init__.py
terrastack/core.py
terrastack-1.0.0.dist-info/LICENSE
terrastack-1.0.0.dist-info/METADATA
terrastack-1.0.0.dist-info/WHEEL
terrastack-1.0.0.dist-info/top_level.txt
terrastack-1.0.0.dist-info/RECORD
