Metadata-Version: 2.1
Name: terrastack
Version: 1.0.0
Summary: Create terraform specifications with code
Home-page: https://github.com/frankotron/terrastack
Author: Frank Hammar
Author-email: frank@frankotron.se
License: MIT
Platform: UNKNOWN
Classifier: License :: OSI Approved :: MIT License
Classifier: Programming Language :: Python
Classifier: Programming Language :: Python :: 3
Classifier: Programming Language :: Python :: 3.6
Classifier: Programming Language :: Python :: Implementation :: CPython
Classifier: Programming Language :: Python :: Implementation :: PyPy
Requires-Python: >=3.6.0
